lumby/__init__.py
lumby/cli.py
lumby/logging/AppLogger.py
lumby/logging/__init__.py
lumby/models/CommandResult.py
lumby/models/Config.py
lumby/models/DiagnosisResult.py
lumby/models/__init__.py
lumby/prompts/default.md
lumby/services/CommandExecutor.py
lumby/services/ConfigLoader.py
lumby/services/DiagnosisService.py
lumby/services/PromptRenderer.py
lumby/services/__init__.py
lumby-0.1.2.dist-info/METADATA
lumby-0.1.2.dist-info/WHEEL
lumby-0.1.2.dist-info/entry_points.txt
lumby-0.1.2.dist-info/licenses/LICENSE
lumby-0.1.2.dist-info/RECORD
