Metadata-Version: 2.4
Name: lumby
Version: 0.1.2
Summary: Smart command wrapper with AI-powered failure diagnosis
Project-URL: Homepage, https://github.com/RasmusGodske/lumby
Project-URL: Documentation, https://github.com/RasmusGodske/lumby#readme
Project-URL: Repository, https://github.com/RasmusGodske/lumby
Project-URL: Issues, https://github.com/RasmusGodske/lumby/issues
Project-URL: Changelog, https://github.com/RasmusGodske/lumby/releases
Author: Rasmus Godske
Maintainer: Rasmus Godske
License-Expression: MIT
License-File: LICENSE
Keywords: ai,anthropic,automation,claude,cli,command-line,debugging,developer-tools,diagnosis
Classifier: Development Status :: 4 - Beta
Classifier: Environment :: Console
Classifier: Intended Audience :: Developers
Classifier: License :: OSI Approved :: MIT License
Classifier: Operating System :: OS Independent
Classifier: Programming Language :: Python :: 3
Classifier: Programming Language :: Python :: 3.11
Classifier: Programming Language :: Python :: 3.12
Classifier: Programming Language :: Python :: 3.13
Classifier: Topic :: Software Development :: Debuggers
Classifier: Topic :: Software Development :: Quality Assurance
Classifier: Topic :: Utilities
Classifier: Typing :: Typed
Requires-Python: >=3.11
Requires-Dist: claude-agent-sdk>=0.1.0
Provides-Extra: dev
Requires-Dist: mypy>=1.0; extra == 'dev'
Requires-Dist: pytest-asyncio>=0.23; extra == 'dev'
Requires-Dist: pytest>=8.0; extra == 'dev'
Requires-Dist: ruff>=0.1; extra == 'dev'
